MANIFEST.in
setup.py
appomatic_renderable/__app__.py
appomatic_renderable/__init__.py
appomatic_renderable/__urls__.py
appomatic_renderable/admin.py
appomatic_renderable/models.py
appomatic_renderable/templateprocessor.py
appomatic_renderable/views.py
appomatic_renderable.egg-info/PKG-INFO
appomatic_renderable.egg-info/SOURCES.txt
appomatic_renderable.egg-info/dependency_links.txt
appomatic_renderable.egg-info/requires.txt
appomatic_renderable.egg-info/top_level.txt
appomatic_renderable/templates/appomatic_renderable/base.html
appomatic_renderable/templates/appomatic_renderable/models/Article/excerpt.html
appomatic_renderable/templates/appomatic_renderable/models/Article/item.rss
appomatic_renderable/templates/appomatic_renderable/models/Article/page.html
appomatic_renderable/templates/appomatic_renderable/models/Collection/list.html
appomatic_renderable/templates/appomatic_renderable/models/Collection/page.html
appomatic_renderable/templates/appomatic_renderable/models/File/excerpt.html
appomatic_renderable/templates/appomatic_renderable/models/File/item.rss
appomatic_renderable/templates/appomatic_renderable/models/File/page.html
appomatic_renderable/templates/appomatic_renderable/models/Image/excerpt.html
appomatic_renderable/templates/appomatic_renderable/models/Image/inline.html
appomatic_renderable/templates/appomatic_renderable/models/Image/item.rss
appomatic_renderable/templates/appomatic_renderable/models/Image/page.html
appomatic_renderable/templates/appomatic_renderable/models/Node/excerpt.html
appomatic_renderable/templates/appomatic_renderable/models/Node/inline.html
appomatic_renderable/templates/appomatic_renderable/models/Node/item.rss
appomatic_renderable/templates/appomatic_renderable/models/Node/page.html
appomatic_renderable/templates/appomatic_renderable/models/Node/page.rss
appomatic_renderable/templates/appomatic_renderable/models/Node-list/page.html
appomatic_renderable/templates/appomatic_renderable/models/Node-list/page.rss
appomatic_renderable/templates/appomatic_renderable/models/Renderable/iframe.html
appomatic_renderable/templates/appomatic_renderable/models/StaticTemplate/MainMenu/excerpt.html
