Metadata-Version: 1.0
Name: appomatic-renderable
Version: 0.0.4
Summary: Renderable is a mini cms framework to make django models easily 'renderable' using templates.
Home-page: http://github.com/redhog/appomatic_renderable
Author: RedHog (Egil Moeller)
Author-email: egil.moller@piratpartiet.se
License: GPL
Keywords: appomatic django cms
Platform: UNKNOWN
